dbv/__init__.py
dbv/py.typed
dbv-0.0.0.dist-info/METADATA
dbv-0.0.0.dist-info/WHEEL
dbv-0.0.0.dist-info/licenses/LICENSE
dbv-0.0.0.dist-info/RECORD
